dancingninjas/__init__.py
dancingninjas/hello.py
dancingninjas-0.1.0.dist-info/METADATA
dancingninjas-0.1.0.dist-info/WHEEL
dancingninjas-0.1.0.dist-info/licenses/LICENSE
dancingninjas-0.1.0.dist-info/RECORD
