Metadata-Version: 2.4
Name: dancingninjas
Version: 0.1.0
Summary: A tiny example package for testing PyPI uploads
Project-URL: Homepage, https://github.com/yourname/dancingninjas
Project-URL: Issues, https://github.com/yourname/dancingninjas/issues
Author-email: Your Name <you@example.com>
License: MIT License
License-File: LICENSE
Keywords: demo,example,ninjas
Classifier: License :: OSI Approved :: MIT License
Classifier: Operating System :: OS Independent
Classifier: Programming Language :: Python :: 3
Requires-Python: >=3.8
